{
 "dependencies": [],
 "tasks": {
  "find_scroll": {
   "title": "Find the Eye Synthesis scroll",
   "icon": {
    "item": {
     "id": "historystages:research_scroll",
     "count": 1
    },
    "type": "heracles:item"
   },
   "type": "heracles:check"
  },
  "research_scroll": {
   "title": "Research the Eye Synthesis scroll",
   "icon": {
    "item": {
     "id": "end_remastered_promax:ancient_eye",
     "count": 1
    },
    "type": "heracles:item"
   },
   "type": "heracles:command",
   "command": "history unlock eye_synthesis"
  }
 },
 "rewards": {
  "coin": {
   "item": {
    "id": "numismatics:crown",
    "count": 2
   },
   "type": "heracles:item"
  }
 },
 "display": {
  "title": {
   "text": "Eye Synthesis"
  },
  "subtitle": {
   "text": "Knowledge waits where the dead left it."
  },
  "description": [
   "\"The Heir line carries this. Only the Heir line.\"",
   "",
   "Already populated. ER ProMax fused eyes (vault_eye etc.).",
   "",
   "This scroll unlocks 21 items.",
   "",
   "Look for it in:",
   "  · End City Treasure",
   "  · Ancient City Ice Box",
   "",
   "→ Find the scroll [discovery]",
   "→ Research [Eye Synthesis] [auto]"
  ],
  "groups": {
   "The Eleven-Eyed Hunt": {
    "position": [
     300,
     300
    ]
   }
  },
  "icon": {
   "item": {
    "id": "end_remastered_promax:ancient_eye",
    "count": 1
   },
   "type": "heracles:item"
  },
  "icon_background": "heracles:textures/gui/quest_backgrounds/circles.png"
 },
 "settings": {
  "showDependencyArrow": true,
  "repeatable": false,
  "autoClaimRewards": false,
  "individual_progress": true,
  "hidden": "LOCKED",
  "unlockNotification": false
 }
}