{
  "dependencies": [
    "ch03_r_smith3"
  ],
  "tasks": {
    "scroll_found": {
      "type": "heracles:advancement",
      "advancement": "sinborn:scrolls/armorcraft"
    },
    "full_set": {
      "title": "Craft a full set of iron armor (chestplate, leggings, helmet, boots)",
      "icon": {
        "item": {
          "id": "minecraft:iron_chestplate",
          "count": 1
        },
        "type": "heracles:item"
      },
      "type": "heracles:check"
    }
  },
  "rewards": {
    "iron_chestplate": {
      "item": {
        "id": "minecraft:iron_chestplate",
        "count": 1
      },
      "type": "heracles:item"
    },
    "coin": {
      "item": {
        "id": "numismatics:sprocket",
        "count": 12
      },
      "type": "heracles:item"
    }
  },
  "display": {
    "title": {
      "translate": "Armorcraft"
    },
    "subtitle": {
      "text": "Iron stops most of what wants to kill you. For now."
    },
    "description": [
      "◆━━━━━━━━━━━━━━━━━━━━━━━━━━━━━━◆",
      "  CH.03 · ARMORCRAFT",
      "◆━━━━━━━━━━━━━━━━━━━━━━━━━━━━━━◆",
      "",
      "▸ Dungeons & Combat adds 7 new armor materials",
      "  and modifies how protection scales.",
      "  Iron is not the end. It is the beginning.",
      "",
      "◈ ARMOR TIERS (DUNGEONS & COMBAT)",
      "  └ Iron: baseline protection",
      "  └ Chainmail: lighter than iron, fast movement",
      "  └ Diamond: strong, expensive, enchantable",
      "  └ Netherite: resistant to fire + knockback",
      "  └ D&C Unique: Forgotten Knight, Titan, Oni Slayer,",
      "    Exiled armor — class-specific stat bonuses",
      "",
      "◈ COLD SWEAT + ARMOR",
      "  └ Certain armor adds insulation",
      "  └ Fur/leather armor = warm insulation",
      "  └ Metal armor = cold conduction (freezes you faster)",
      "  └ Ch09 introduces Cold Sweat insulation items",
      "  └ Balance temperature resistance with armor protection",
      "",
      "◈ SCROLL: Armorcraft",
      "  └ Found in: armorer chests, forge ruins,",
      "    warrior barracks, combat guild archives",
      "  └ Research time: 20 min",
      "  └ Unlocks: D&C armor tier knowledge,",
      "    Cold Sweat + armor interaction awareness",
      "",
      "▸ The scroll describes armor as skin.",
      "  Not protection. Skin.",
      "  The first thing between you and everything else.",
      "",
      "▶ Find The Armorcraft scroll [check]",
      "▶ Craft a full iron armor set [check]",
      "",
      "◇ Scales & Steel scroll (below this chain)",
      "  covers combat damage math and class scaling.",
      "  Read it before the first boss."
    ],
    "groups": {
      "The Rotting Gate": {
        "position": [
          -450,
          450
        ]
      }
    },
    "icon": {
      "item": {
        "id": "minecraft:iron_chestplate",
        "count": 1
      },
      "type": "heracles:item"
    },
    "icon_background": "heracles:textures/gui/quest_backgrounds/gears.png"
  },
  "settings": {
    "showDependencyArrow": true,
    "repeatable": false,
    "autoClaimRewards": false,
    "individual_progress": true,
    "hidden": "LOCKED",
    "unlockNotification": false
  }
}
