{
  "display_name": "Numismatic Mechanisms",
  "research_time": 5400,
  "items": [
    "createnumrec:incomplete_bevel",
    "createnumrec:incomplete_cog",
    "createnumrec:incomplete_crown",
    "createnumrec:incomplete_sprocket",
    "createnumrec:incomplete_spur",
    "createnumrec:incomplete_sun",
    "numismatics:andesite_depositor",
    "numismatics:bank_terminal",
    "numismatics:banking_guide",
    "numismatics:bevel",
    "numismatics:black_card",
    "numismatics:black_id_card",
    "numismatics:blaze_banker",
    "numismatics:blue_card",
    "numismatics:blue_id_card",
    "numismatics:brass_depositor",
    "numismatics:brown_card",
    "numismatics:brown_id_card",
    "numismatics:cog",
    "numismatics:creative_vendor",
    "numismatics:crown",
    "numismatics:cyan_card",
    "numismatics:cyan_id_card",
    "numismatics:gray_card",
    "numismatics:gray_id_card",
    "numismatics:green_card",
    "numismatics:green_id_card",
    "numismatics:light_blue_card",
    "numismatics:light_blue_id_card",
    "numismatics:light_gray_card",
    "numismatics:light_gray_id_card",
    "numismatics:lime_card",
    "numismatics:lime_id_card",
    "numismatics:magenta_card",
    "numismatics:trusted_block.attempt_break",
    "numismatics:vendor"
  ],
  "tags": [],
  "mods": [],
  "mod_exceptions": [],
  "recipes": [],
  "dimensions": [],
  "structures": [],
  "entities": {
    "attacklock": [],
    "spawnlock": []
  }
}